[
        {
        	"Game":"MI vs GL",
        	"First":"Bindu John",
        	"Second":"Jomon",
        	"Third":"Shanu"
        },
        {
        	"Game":"KKR vs DC",
        	"First":"Naziya",
        	"Second":"Ashok",
        	"Third":"Blesson"
        },
		{
        	"Game":"MI vs GL",
        	"First":"Bindu John",
        	"Second":"Jomon",
        	"Third":"Shanu"
        },
        {
        	"Game":"KKR vs DC",
        	"First":"Naziya",
        	"Second":"Ashok",
        	"Third":"Blesson"
        },
        {
        	"Game":"KKR vs DC",
        	"First":"Naziya",
        	"Second":"Ashok",
        	"Third":"Blesson"
        },
		{
        	"Game":"MI vs GL",
        	"First":"Bindu John",
        	"Second":"Jomon",
        	"Third":"Shanu"
        },
        {
        	"Game":"KKR vs DC",
        	"First":"Naziya",
        	"Second":"Ashok",
        	"Third":"Blesson"
        },
        {
        	"Game":"KKR vs DC",
        	"First":"Naziya",
        	"Second":"Ashok",
        	"Third":"Blesson"
        },
		{
        	"Game":"MI vs GL",
        	"First":"Bindu John",
        	"Second":"Jomon",
        	"Third":"Shanu"
        },
        {
        	"Game":"KKR vs DC",
        	"First":"Naziya",
        	"Second":"Ashok",
        	"Third":"Blesson"
        },
        {
        	"Game":"KKR vs DC",
        	"First":"Naziya",
        	"Second":"Ashok",
        	"Third":"Blesson"
        },
		{
        	"Game":"MI vs GL",
        	"First":"Bindu John",
        	"Second":"Jomon",
        	"Third":"Shanu"
        },
        {
        	"Game":"KKR vs DC",
        	"First":"Naziya",
        	"Second":"Ashok",
        	"Third":"Blesson"
        },
        {
        	"Game":"KKR vs DC",
        	"First":"Naziya",
        	"Second":"Ashok",
        	"Third":"Blesson"
        },
		{
        	"Game":"MI vs GL",
        	"First":"Bindu John",
        	"Second":"Jomon",
        	"Third":"Shanu"
        },
        {
        	"Game":"KKR vs DC",
        	"First":"Naziya",
        	"Second":"Ashok",
        	"Third":"Blesson"
        }

    ]